<?xml version="1.0" encoding="UTF-8" ?>
<webwork-extraction>
  <webwork-reps xml:id="extracted-webwork-1" ww-id="webwork-1">
    <pg source="Library/UVA-Stat/setStat212-Homework02/stat212-HW02-18.pg" />

      
    <static source="Library/UVA-Stat/setStat212-Homework02/stat212-HW02-18.pg" seed="1">
      <statement>
      
      <p>Consider the following data set:
      <me>\begin{array}{ccccccccc} 
      39 \amp  20 \amp  36 \amp  27 \amp  51 \amp  27 \amp  12 \amp  16 \amp  12\\
      51 \amp  39 \amp  28 \amp  51 \amp  13 \amp  27 \amp  34 \amp  49 \amp  40  
      \end{array}</me></p>
      <p>Find the 15th and 88th percentiles for this data.</p>
      <p>15th percentile = <fillin name="AnSwEr0001" characters="15" /></p>
      <p>88th percentile = <fillin name="AnSwEr0002" characters="15" /></p>
      </statement>
      
      
    </static>
      
    <server-url hint="yes" solution="yes">https://webwork-ptx.aimath.org/webwork2/html2xml?courseID=anonymous&amp;userID=anonymous&amp;password=anonymous&amp;course_password=anonymous&amp;answersSubmitted=0&amp;displayMode=MathJax&amp;outputformat=simple&amp;problemSeed=1&amp;sourceFilePath=Library/UVA-Stat/setStat212-Homework02/stat212-HW02-18.pg</server-url>

    <server-url hint="yes" solution="no">https://webwork-ptx.aimath.org/webwork2/html2xml?courseID=anonymous&amp;userID=anonymous&amp;password=anonymous&amp;course_password=anonymous&amp;answersSubmitted=0&amp;displayMode=MathJax&amp;outputformat=simple&amp;problemSeed=1&amp;sourceFilePath=Library/UVA-Stat/setStat212-Homework02/stat212-HW02-18.pg</server-url>

    <server-url hint="no" solution="yes">https://webwork-ptx.aimath.org/webwork2/html2xml?courseID=anonymous&amp;userID=anonymous&amp;password=anonymous&amp;course_password=anonymous&amp;answersSubmitted=0&amp;displayMode=MathJax&amp;outputformat=simple&amp;problemSeed=1&amp;sourceFilePath=Library/UVA-Stat/setStat212-Homework02/stat212-HW02-18.pg</server-url>

    <server-url hint="no" solution="no">https://webwork-ptx.aimath.org/webwork2/html2xml?courseID=anonymous&amp;userID=anonymous&amp;password=anonymous&amp;course_password=anonymous&amp;answersSubmitted=0&amp;displayMode=MathJax&amp;outputformat=simple&amp;problemSeed=1&amp;sourceFilePath=Library/UVA-Stat/setStat212-Homework02/stat212-HW02-18.pg</server-url>

  </webwork-reps>

  <webwork-reps xml:id="extracted-webwork-2" ww-id="webwork-2">
    <pg source="Library/NAU/setStatistics/FiveNumFromPlot.pg" />

      
    <static source="Library/NAU/setStatistics/FiveNumFromPlot.pg" seed="2">
      <statement>
      
      <p>Consider the following box and whisker plot.  Find the indicated values of the represented data.</p>
      <sidebyside widths="116.666666666667%">
      <image source="images/webwork-2-image-1.png" />
      </sidebyside>
      <p>Median: <fillin name="AnSwEr0001" characters="5" /></p>
      <p>Maximum: <fillin name="AnSwEr0002" characters="5" /></p>
      </statement>
      
      
    </static>
      
    <server-url hint="yes" solution="yes">https://webwork-ptx.aimath.org/webwork2/html2xml?courseID=anonymous&amp;userID=anonymous&amp;password=anonymous&amp;course_password=anonymous&amp;answersSubmitted=0&amp;displayMode=MathJax&amp;outputformat=simple&amp;problemSeed=2&amp;sourceFilePath=Library/NAU/setStatistics/FiveNumFromPlot.pg</server-url>

    <server-url hint="yes" solution="no">https://webwork-ptx.aimath.org/webwork2/html2xml?courseID=anonymous&amp;userID=anonymous&amp;password=anonymous&amp;course_password=anonymous&amp;answersSubmitted=0&amp;displayMode=MathJax&amp;outputformat=simple&amp;problemSeed=2&amp;sourceFilePath=Library/NAU/setStatistics/FiveNumFromPlot.pg</server-url>

    <server-url hint="no" solution="yes">https://webwork-ptx.aimath.org/webwork2/html2xml?courseID=anonymous&amp;userID=anonymous&amp;password=anonymous&amp;course_password=anonymous&amp;answersSubmitted=0&amp;displayMode=MathJax&amp;outputformat=simple&amp;problemSeed=2&amp;sourceFilePath=Library/NAU/setStatistics/FiveNumFromPlot.pg</server-url>

    <server-url hint="no" solution="no">https://webwork-ptx.aimath.org/webwork2/html2xml?courseID=anonymous&amp;userID=anonymous&amp;password=anonymous&amp;course_password=anonymous&amp;answersSubmitted=0&amp;displayMode=MathJax&amp;outputformat=simple&amp;problemSeed=2&amp;sourceFilePath=Library/NAU/setStatistics/FiveNumFromPlot.pg</server-url>

  </webwork-reps>

</webwork-extraction>